nufhe/__init__.py
nufhe/api_high_level.py
nufhe/api_low_level.py
nufhe/blind_rotate.mako
nufhe/blind_rotate.py
nufhe/bootstrap.py
nufhe/computation_cache.py
nufhe/gates.py
nufhe/lwe.py
nufhe/lwe_cpu.py
nufhe/lwe_gpu.mako
nufhe/lwe_gpu.py
nufhe/numeric_functions.py
nufhe/numeric_functions_cpu.py
nufhe/numeric_functions_gpu.py
nufhe/operators_integer.py
nufhe/performance.py
nufhe/polynomial_transform.py
nufhe/polynomial_transform_fft.py
nufhe/polynomial_transform_ntt.py
nufhe/polynomials.py
nufhe/polynomials_cpu.py
nufhe/polynomials_gpu.mako
nufhe/polynomials_gpu.py
nufhe/random_numbers.py
nufhe/tgsw.py
nufhe/tgsw_cpu.py
nufhe/tgsw_gpu.mako
nufhe/tgsw_gpu.py
nufhe/tlwe.py
nufhe/tlwe_cpu.py
nufhe/tlwe_gpu.mako
nufhe/tlwe_gpu.py
nufhe/utils.py
nufhe/transform/__init__.py
nufhe/transform/arithmetic.mako
nufhe/transform/arithmetic.py
nufhe/transform/computation.mako
nufhe/transform/computation.py
nufhe/transform/fft.mako
nufhe/transform/fft.py
nufhe/transform/ntt.mako
nufhe/transform/ntt.py
nufhe/transform/ntt_cpu.py
nufhe-0.0.3.dist-info/DESCRIPTION.rst
nufhe-0.0.3.dist-info/METADATA
nufhe-0.0.3.dist-info/RECORD
nufhe-0.0.3.dist-info/WHEEL
nufhe-0.0.3.dist-info/metadata.json
nufhe-0.0.3.dist-info/top_level.txt
nufhe-0.0.3.dist-info/zip-safe
